measurements/__init__.py
measurements/constants.py
measurements/all/__init__.py
measurements/all/box/__init__.py
measurements/all/box/constants.py
measurements/all/box/data.py
measurements/all/box/save_values.py
measurements/all/pw/__init__.py
measurements/all/pw/data.py
measurements/dop/__init__.py
measurements/dop/constants.py
measurements/dop/box/__init__.py
measurements/dop/box/constants.py
measurements/dop/box/load.py
measurements/dop/box/regrid.py
measurements/dop/pw/__init__.py
measurements/dop/pw/constants.py
measurements/dop/pw/data.py
measurements/land_sea_mask/__init__.py
measurements/land_sea_mask/constants.py
measurements/land_sea_mask/depth.py
measurements/land_sea_mask/load.py
measurements/land_sea_mask/lsm.py
measurements/plot/__init__.py
measurements/plot/distibution.py
measurements/po4/__init__.py
measurements/po4/constants.py
measurements/po4/woa/__init__.py
measurements/po4/woa/data09/__init__.py
measurements/po4/woa/data09/constants.py
measurements/po4/woa/data09/load.py
measurements/po4/woa/data09/regrid.py
measurements/po4/woa/data13/__init__.py
measurements/po4/woa/data13/constants.py
measurements/po4/woa/data13/load.py
measurements/po4/woa/data13/regrid.py
measurements/po4/woa/data13/save.py
measurements/po4/woa/plot/__init__.py
measurements/po4/woa/plot/interface.py
measurements/po4/woa/plot/sample_deviation.py
measurements/po4/woa/plot/sample_mean.py
measurements/po4/woa/plot/sample_nob.py
measurements/po4/wod/__init__.py
measurements/po4/wod/constants.py
measurements/po4/wod/cruise.py
measurements/po4/wod/data.py
measurements/po4/wod/dict.py
measurements/po4/wod/values.py
measurements/po4/wod/plot/__init__.py
measurements/po4/wod/plot/correlation.py
measurements/po4/wod/plot/correlogram.py
measurements/po4/wod/plot/data.py
measurements/po4/wod/plot/interface.py
measurements/po4/wod/plot/value_histograms.py
measurements/universal/__init__.py
measurements/universal/constants.py
measurements-0.1.1.dev67.dist-info/DESCRIPTION.rst
measurements-0.1.1.dev67.dist-info/METADATA
measurements-0.1.1.dev67.dist-info/RECORD
measurements-0.1.1.dev67.dist-info/WHEEL
measurements-0.1.1.dev67.dist-info/metadata.json
measurements-0.1.1.dev67.dist-info/top_level.txt
