Metadata-Version: 2.0
Name: measurements
Version: 0.1.1.dev67
Summary: measurements functions
Home-page: https://github.com/jor-/measurements
Author: Joscha Reimer
Author-email: jor@informatik.uni-kiel.de
License: GPLv3+
Keywords: measurements functions
Platform: UNKNOWN
Classifier: Development Status :: 3 - Alpha
Classifier: Intended Audience :: Developers
Classifier: Intended Audience :: Science/Research
Classifier: Topic :: Software Development :: Libraries :: Python Modules
Classifier: License :: OSI Approved :: GNU General Public License v3 or later (GPLv3+)
Classifier: Programming Language :: Python :: 3
Requires-Dist: numpy
Requires-Dist: scipy
Requires-Dist: utillib[options,cache,cholmod,interpolate]
Provides-Extra: plot
Requires-Dist: matplotlib; extra == 'plot'
Requires-Dist: utillib[plot]; extra == 'plot'
Provides-Extra: sorted_measurements_dict
Requires-Dist: utillib[sorted_multi_dict]; extra == 'sorted_measurements_dict'
